{"title":"오디오클립 ─ 삼프로TV 경제의 신과함께","url":"https://audioclip.naver.com/channels/6519","favicon":"https://audioclip.naver.com/channels/favicon.ico","elements":[{"title":"[마켓 인사이드] 국내 전망, 1분기는 상승 전망? f. 교보증권 박병창 이사","contents":"<span class=\"blind\">재생시간</span>25분","link":"https://audioclip.naver.com/channels/6519/clips/14651","retrieved":1704156196440,"image":"https://audio-phinf.pstatic.net/20240102_295/1704153334873Cl7HG_JPEG/00%BE%F7%B7%CE%B5%E5%BF%EB.jpg?type=f150_150"},{"title":"[미스터마켓] 소프트랜딩 기대감에 부푼 월스트리트…'장밋빛 전망' 확산? f.김프로","contents":"<span class=\"blind\">재생시간</span>17분","link":"https://audioclip.naver.com/channels/6519/clips/14650","retrieved":1704156196441,"image":"https://audio-phinf.pstatic.net/20240102_276/1704152160358mDFyr_JPEG/00%BE%F7%B7%CE%B5%E5%BF%EB.jpg?type=f150_150"},{"title":"[뉴스3+] 日서 한신대지진보다 큰 규모 7.6 강진…한때 대형 쓰나미 경보 f.권순우 취재팀장","contents":"<span class=\"blind\">재생시간</span>26분","link":"https://audioclip.naver.com/channels/6519/clips/14649","retrieved":1704156196443,"image":"https://audio-phinf.pstatic.net/20240102_221/17041516575820l1UK_JPEG/00%BE%F7%B7%CE%B5%E5%BF%EB.jpg?type=f150_150"},{"title":"[월스트리트 모닝브리핑] 2023년 마지막 거래일 '약세'…2024년 거래 전망은? f.여도은, 오기석,이완수","contents":"<span class=\"blind\">재생시간</span>55분","link":"https://audioclip.naver.com/channels/6519/clips/14648","retrieved":1704150707841},{"title":"[신과대화: 조봉한 깨봉수학 대표] 은행보다 빨리 수익 계산 하는 법","contents":"<span class=\"blind\">재생시간</span>58분","link":"https://audioclip.naver.com/channels/6519/clips/14645","retrieved":1704082448541},{"title":"[집으로 특집편] 다시 모인 집으로!! 2024 부동산 전망은?!","contents":"<span class=\"blind\">재생시간</span>49분","link":"https://audioclip.naver.com/channels/6519/clips/14642","retrieved":1704074430772},{"title":"[2024년 경제전망 2부] PF 부실 언제 무엇이 터질지 모른다! f.LG경영연구원 조영무 박사 [신과대화]","contents":"<span class=\"blind\">재생시간</span>47분","link":"https://audioclip.naver.com/channels/6519/clips/14647","retrieved":1704070115278},{"title":"[2024년 경제전망 1부] 글로벌 장기 저성장이 시작될 것!  f.LG경영연구원 조영무 박사 [신과대화]","contents":"<span class=\"blind\">재생시간</span>44분","link":"https://audioclip.naver.com/channels/6519/clips/14646","retrieved":1704064273312},{"title":"[주말인터뷰] 발발하는 전쟁 속 떠오르는 K-군함","contents":"<span class=\"blind\">재생시간</span>38분","link":"https://audioclip.naver.com/channels/6519/clips/14644","retrieved":1703999454841},{"title":"[주말인터뷰] 떠오르는 해양 산업, 한국 조선업계의 기회?","contents":"<span class=\"blind\">재생시간</span>41분","link":"https://audioclip.naver.com/channels/6519/clips/14643","retrieved":1703995994236}]}