{"title":"오디오클립 ─ CBS 김현정의 뉴스쇼","url":"https://audioclip.naver.com/channels/1256","favicon":"https://audioclip.naver.com/channels/favicon.ico","elements":[{"title":"[2023/11/08] 고민정 “한동훈 탄핵하려면 하라? 대단한 관종... 출마? 파괴력도 별로”","contents":"<span class=\"blind\">재생시간</span>23분","link":"https://audioclip.naver.com/channels/1256/clips/10277","retrieved":1699408090650,"image":"https://audio-phinf.pstatic.net/20230628_215/1687886430058Tgl56_JPEG/image.jpg?type=f150_150"},{"title":"[2023/11/08] 윤희숙 \"안철수 이준석 복국집 옆방... 고성? 서로 끌리는 듯\"","contents":"<span class=\"blind\">재생시간</span>23분","link":"https://audioclip.naver.com/channels/1256/clips/10278","retrieved":1699408090653,"image":"https://audio-phinf.pstatic.net/20230628_215/1687886430058Tgl56_JPEG/image.jpg?type=f150_150"},{"title":"[2023/11/08] 반기성 “올 겨울? 따뜻한데 엄청 춥다... 엘니뇨와 북극한파 때문”","contents":"<span class=\"blind\">재생시간</span>13분","link":"https://audioclip.naver.com/channels/1256/clips/10279","retrieved":1699408090661,"image":"https://audio-phinf.pstatic.net/20230628_215/1687886430058Tgl56_JPEG/image.jpg?type=f150_150"},{"title":"[2023/11/08] [놓지마 뉴스]","contents":"<span class=\"blind\">재생시간</span>4분","link":"https://audioclip.naver.com/channels/1256/clips/10280","retrieved":1699408090664,"image":"https://audio-phinf.pstatic.net/20230628_215/1687886430058Tgl56_JPEG/image.jpg?type=f150_150"},{"title":"[2023/11/08] [뉴스쇼 방송 전체듣기]","contents":"<span class=\"blind\">재생시간</span>80분","link":"https://audioclip.naver.com/channels/1256/clips/10281","retrieved":1699408090667},{"title":"[2023/11/08] [뉴스 연구소] 인요한 뼈때린 김종인 “환자는 000”","contents":"<span class=\"blind\">재생시간</span>15분","link":"https://audioclip.naver.com/channels/1256/clips/10282","retrieved":1699410062886},{"title":"[2023/11/07] [돌쇠 토론] 이준석, 조국 신당? “초대장 뿌리고... 실무 준비 중”","contents":"<span class=\"blind\">재생시간</span>25분","link":"https://audioclip.naver.com/channels/1256/clips/10271","retrieved":1699326709205},{"title":"[2023/11/07] 이상민 “이준석 신당 합류? 가능성 열려있다... 한 달 안에 결정”","contents":"<span class=\"blind\">재생시간</span>16분","link":"https://audioclip.naver.com/channels/1256/clips/10273","retrieved":1699326709207},{"title":"[2023/11/07] 박정호 “공매도 금지 약발... 왜 하루를 못 갔을까?”","contents":"<span class=\"blind\">재생시간</span>14분","link":"https://audioclip.naver.com/channels/1256/clips/10272","retrieved":1699326709209},{"title":"[2023/11/07] [놓지마 뉴스]","contents":"<span class=\"blind\">재생시간</span>6분","link":"https://audioclip.naver.com/channels/1256/clips/10274","retrieved":1699326709213}]}