{"title":"오디오클립 ─ CBS 김현정의 뉴스쇼","url":"https://audioclip.naver.com/channels/1256","favicon":"https://audioclip.naver.com/channels/favicon.ico","elements":[{"title":"[2022/05/02] 최고 실적 삼전, 왜 6만전자? \"그나마 버텨서 그 정도\"","contents":"<span class=\"blind\">재생시간</span>13분","link":"https://audioclip.naver.com/channels/1256/clips/7811","retrieved":1651461822931,"image":"https://audio-phinf.pstatic.net/20220502_72/1651455885886Wv5R6_JPEG/ef736b6917aba7431692873b91ac4c5081af42ebd5efbcce5132f02819a62ddcc05eb3dc54c28b2e.jpeg?type=f150_150"},{"title":"[2022/05/02] [뉴스닥] 이재명 등판론? 김근식 \"명분 없어\" vs 장경태 \"윤심 대항마로\"","contents":"<span class=\"blind\">재생시간</span>27분","link":"https://audioclip.naver.com/channels/1256/clips/7812","retrieved":1651461822936,"image":"https://audio-phinf.pstatic.net/20220502_225/1651455887424adb4d_JPEG/ef736b6917aba7431692873b91ac4c5081af42ebd5efbcce5132f02819a62ddcc05eb3dc54c28b2e.jpeg?type=f150_150"},{"title":"[2022/05/02] [뉴스 연구소] 국회, 또 폭풍전야","contents":"<span class=\"blind\">재생시간</span>15분","link":"https://audioclip.naver.com/channels/1256/clips/7809","retrieved":1651461822937,"image":"https://audio-phinf.pstatic.net/20220502_144/1651454089112g0Wvq_JPEG/ef736b6917aba7431692873b91ac4c5081af42ebd5efbcce5132f02819a62ddcc05eb3dc54c28b2e.jpeg?type=f150_150"},{"title":"[2022/05/02] 김용태 \"사면이 편의점 1+1인가.. MB-김경수 흥정 안돼\"","contents":"<span class=\"blind\">재생시간</span>16분","link":"https://audioclip.naver.com/channels/1256/clips/7810","retrieved":1651461822938,"image":"https://audio-phinf.pstatic.net/20220502_173/1651454089611ClmAA_JPEG/ef736b6917aba7431692873b91ac4c5081af42ebd5efbcce5132f02819a62ddcc05eb3dc54c28b2e.jpeg?type=f150_150"},{"title":"[2022/05/02] [놓지마 뉴스]","contents":"<span class=\"blind\">재생시간</span>5분","link":"https://audioclip.naver.com/channels/1256/clips/7807","retrieved":1651452926029},{"title":"[2022/05/02] [뉴스쇼 방송 전체듣기]","contents":"<span class=\"blind\">재생시간</span>81분","link":"https://audioclip.naver.com/channels/1256/clips/7808","retrieved":1651452926030},{"title":"[2022/04/29] [댓꿀쇼] 尹·장제원 국민투표추진 | 중수청 증발과 필리버스터 | 스티브유 비자 거부 적법: 20년 소송사","contents":"<span class=\"blind\">재생시간</span>78분","link":"https://audioclip.naver.com/channels/1256/clips/7801","retrieved":1651292414495},{"title":"[2022/04/29] 강유미 \"현실고증 롤플레잉 연기의 비결은..\"","contents":"<span class=\"blind\">재생시간</span>12분","link":"https://audioclip.naver.com/channels/1256/clips/7802","retrieved":1651292414498},{"title":"[2022/04/29] 설훈 \"정경심, 김경수 사면 해야\" vs 김기현 \"MB가 먼저\"","contents":"<span class=\"blind\">재생시간</span>23분","link":"https://audioclip.naver.com/channels/1256/clips/7803","retrieved":1651292414499},{"title":"[2022/04/29] [놓지마 뉴스]","contents":"<span class=\"blind\">재생시간</span>2분","link":"https://audioclip.naver.com/channels/1256/clips/7804","retrieved":1651292414509}]}