{"title":"오디오클립 ─ 채널A 뉴스A","url":"https://audioclip.naver.com/channels/3117","favicon":"https://audioclip.naver.com/channels/favicon.ico","elements":[{"title":"12월 4일 (월) 뉴스A","contents":"<span class=\"blind\">재생시간</span>56분","link":"https://audioclip.naver.com/channels/3117/clips/1593","retrieved":1701709807921,"image":"https://audio-phinf.pstatic.net/20230628_157/1687886527837MKyTG_PNG/e6b8802c632ba6d1c3181933ed939dbf.png?type=f150_150"},{"title":"12월 03일 (일) 뉴스A","contents":"<span class=\"blind\">재생시간</span>41분","link":"https://audioclip.naver.com/channels/3117/clips/1592","retrieved":1701616168274,"image":"https://audio-phinf.pstatic.net/20230628_157/1687886527837MKyTG_PNG/e6b8802c632ba6d1c3181933ed939dbf.png?type=f150_150"},{"title":"12월 01일 (금) 뉴스A","contents":"<span class=\"blind\">재생시간</span>52분","link":"https://audioclip.naver.com/channels/3117/clips/1590","retrieved":1701450587377,"image":"https://audio-phinf.pstatic.net/20230628_157/1687886527837MKyTG_PNG/e6b8802c632ba6d1c3181933ed939dbf.png?type=f150_150"},{"title":"12월 02일 (토) 뉴스A","contents":"<span class=\"blind\">재생시간</span>39분","link":"https://audioclip.naver.com/channels/3117/clips/1591","retrieved":1701526125519,"image":"https://audio-phinf.pstatic.net/20230628_157/1687886527837MKyTG_PNG/e6b8802c632ba6d1c3181933ed939dbf.png?type=f150_150"},{"title":"11월 30일 (목) 뉴스A","contents":"<span class=\"blind\">재생시간</span>57분","link":"https://audioclip.naver.com/channels/3117/clips/1589","retrieved":1701367989887},{"title":"11월 29일 (수) 뉴스A","contents":"<span class=\"blind\">재생시간</span>57분","link":"https://audioclip.naver.com/channels/3117/clips/1588","retrieved":1701274406179},{"title":"11월 28일 (화) 뉴스A","contents":"<span class=\"blind\">재생시간</span>59분","link":"https://audioclip.naver.com/channels/3117/clips/1587","retrieved":1701191392111},{"title":"11월 27일 (월) 뉴스A","contents":"<span class=\"blind\">재생시간</span>58분","link":"https://audioclip.naver.com/channels/3117/clips/1586","retrieved":1701101596349},{"title":"11월 26일 (일) 뉴스A","contents":"<span class=\"blind\">재생시간</span>41분","link":"https://audioclip.naver.com/channels/3117/clips/1585","retrieved":1701018544596},{"title":"11월 25일 (토) 뉴스A","contents":"<span class=\"blind\">재생시간</span>9분","link":"https://audioclip.naver.com/channels/3117/clips/1584","retrieved":1700914580867}]}