{"title":"오디오클립 ─ JTBC 뉴스룸","url":"https://audioclip.naver.com/channels/2946","favicon":"https://audioclip.naver.com/channels/favicon.ico","elements":[{"title":"2022년 7월 4일 (월) JTBC 뉴스룸","contents":"<span class=\"blind\">재생시간</span>69분","link":"https://audioclip.naver.com/channels/2946/clips/1355","retrieved":1656948035007,"image":"https://audio-phinf.pstatic.net/20220704_17/1656945838949rkB9o_JPEG/a20963544e5de908f840addfb66290c4.jpg?type=f150_150"},{"title":"2022년 7월 3일 (일) JTBC 뉴스룸","contents":"<span class=\"blind\">재생시간</span>36분","link":"https://audioclip.naver.com/channels/2946/clips/1354","retrieved":1656854408040,"image":"https://audio-phinf.pstatic.net/20220703_287/1656852226220h98m4_JPEG/a20963544e5de908f840addfb66290c4.jpg?type=f150_150"},{"title":"2022년 7월 2일 (토) JTBC 뉴스룸","contents":"<span class=\"blind\">재생시간</span>35분","link":"https://audioclip.naver.com/channels/2946/clips/1353","retrieved":1656764252650,"image":"https://audio-phinf.pstatic.net/20220702_144/1656762236751maqU3_JPEG/a20963544e5de908f840addfb66290c4.jpg?type=f150_150"},{"title":"2022년 7월 1일 (금) JTBC 뉴스룸","contents":"<span class=\"blind\">재생시간</span>59분","link":"https://audioclip.naver.com/channels/2946/clips/1352","retrieved":1656684600405,"image":"https://audio-phinf.pstatic.net/20220701_287/1656683078473uziyN_JPEG/a20963544e5de908f840addfb66290c4.jpg?type=f150_150"},{"title":"2022년 6월 30일 (목) JTBC 뉴스룸","contents":"<span class=\"blind\">재생시간</span>68분","link":"https://audioclip.naver.com/channels/2946/clips/1351","retrieved":1656598249491},{"title":"2022년 6월 29일 (수) JTBC 뉴스룸","contents":"<span class=\"blind\">재생시간</span>70분","link":"https://audioclip.naver.com/channels/2946/clips/1350","retrieved":1656511799725},{"title":"2022년 6월 28일 (화) JTBC 뉴스룸","contents":"<span class=\"blind\">재생시간</span>68분","link":"https://audioclip.naver.com/channels/2946/clips/1349","retrieved":1656425500185},{"title":"2022년 6월 27일 (월) JTBC 뉴스룸","contents":"<span class=\"blind\">재생시간</span>68분","link":"https://audioclip.naver.com/channels/2946/clips/1348","retrieved":1656339144541},{"title":"2022년 6월 26일 (일) JTBC 뉴스룸","contents":"<span class=\"blind\">재생시간</span>37분","link":"https://audioclip.naver.com/channels/2946/clips/1347","retrieved":1656249702594},{"title":"2022년 6월 25일 (토) JTBC 뉴스룸","contents":"<span class=\"blind\">재생시간</span>36분","link":"https://audioclip.naver.com/channels/2946/clips/1346","retrieved":1656159410441}]}