{"title":"오디오클립 ─ KBS 뉴스","url":"https://audioclip.naver.com/channels/1847","favicon":"https://audioclip.naver.com/channels/favicon.ico","elements":[{"title":"[09월 16일 05시] 5시 뉴스","contents":"<span class=\"blind\">재생시간</span>4분","link":"https://audioclip.naver.com/channels/1847/clips/18232","retrieved":1663276435514,"image":"https://audio-phinf.pstatic.net/20220916_243/1663272863958fELrL_PNG/logo-icon-1024.png?type=f150_150"},{"title":"[09월 16일 00시] 24시 뉴스","contents":"<span class=\"blind\">재생시간</span>4분","link":"https://audioclip.naver.com/channels/1847/clips/18231","retrieved":1663254888277,"image":"https://audio-phinf.pstatic.net/20220916_202/1663254831111HtknA_PNG/logo-icon-1024.png?type=f150_150"},{"title":"[09월 15일 22시] 22시 뉴스","contents":"<span class=\"blind\">재생시간</span>4분","link":"https://audioclip.naver.com/channels/1847/clips/18230","retrieved":1663249510607,"image":"https://audio-phinf.pstatic.net/20220915_38/1663247676218rSG5p_PNG/logo-icon-1024.png?type=f150_150"},{"title":"[09월 15일 21시] KBS 뉴스 9 (1TV  수중계)","contents":"<span class=\"blind\">재생시간</span>29분","link":"https://audioclip.naver.com/channels/1847/clips/18229","retrieved":1663249510617,"image":"https://audio-phinf.pstatic.net/20220915_200/1663245834112wjD8D_PNG/logo-icon-1024.png?type=f150_150"},{"title":"[09월 15일 19시] 저녁 종합뉴스","contents":"<span class=\"blind\">재생시간</span>19분","link":"https://audioclip.naver.com/channels/1847/clips/18228","retrieved":1663240351710},{"title":"[09월 15일 17시] 17시 뉴스","contents":"<span class=\"blind\">재생시간</span>4분","link":"https://audioclip.naver.com/channels/1847/clips/18227","retrieved":1663229948323},{"title":"[09월 15일 16시] 16시 뉴스","contents":"<span class=\"blind\">재생시간</span>4분","link":"https://audioclip.naver.com/channels/1847/clips/18226","retrieved":1663226808227},{"title":"[09월 15일 14시] 뉴스 중계탑","contents":"<span class=\"blind\">재생시간</span>19분","link":"https://audioclip.naver.com/channels/1847/clips/18225","retrieved":1663221621744},{"title":"[09월 15일 12시] 정오 종합뉴스","contents":"<span class=\"blind\">재생시간</span>19분","link":"https://audioclip.naver.com/channels/1847/clips/18224","retrieved":1663215500610},{"title":"[09월 15일 11시] 11시 뉴스","contents":"<span class=\"blind\">재생시간</span>4분","link":"https://audioclip.naver.com/channels/1847/clips/18223","retrieved":1663215500612}]}