{"title":"오디오클립 ─ KBS 뉴스","url":"https://audioclip.naver.com/channels/1847","favicon":"https://audioclip.naver.com/channels/favicon.ico","elements":[{"title":"[04월 28일 19시] 19시 뉴스","contents":"<span class=\"blind\">재생시간</span>4분","link":"https://audioclip.naver.com/channels/1847/clips/26525","retrieved":1714302538502,"image":"https://audio-phinf.pstatic.net/20230628_269/1687886470882sQaHv_PNG/logo-icon-1024.png?type=f150_150"},{"title":"[04월 28일 18시] 18시 뉴스","contents":"<span class=\"blind\">재생시간</span>4분","link":"https://audioclip.naver.com/channels/1847/clips/26524","retrieved":1714299005497,"image":"https://audio-phinf.pstatic.net/20230628_269/1687886470882sQaHv_PNG/logo-icon-1024.png?type=f150_150"},{"title":"[04월 28일 17시] 17시 뉴스","contents":"<span class=\"blind\">재생시간</span>4분","link":"https://audioclip.naver.com/channels/1847/clips/26523","retrieved":1714292084181,"image":"https://audio-phinf.pstatic.net/20230628_269/1687886470882sQaHv_PNG/logo-icon-1024.png?type=f150_150"},{"title":"[04월 28일 15시] 15시 뉴스","contents":"<span class=\"blind\">재생시간</span>4분","link":"https://audioclip.naver.com/channels/1847/clips/26522","retrieved":1714288245028,"image":"https://audio-phinf.pstatic.net/20230628_269/1687886470882sQaHv_PNG/logo-icon-1024.png?type=f150_150"},{"title":"[04월 28일 14시] 14시 뉴스","contents":"<span class=\"blind\">재생시간</span>4분","link":"https://audioclip.naver.com/channels/1847/clips/26521","retrieved":1714284761539},{"title":"[04월 28일 12시] 정오 종합뉴스","contents":"<span class=\"blind\">재생시간</span>9분","link":"https://audioclip.naver.com/channels/1847/clips/26520","retrieved":1714277541889},{"title":"[04월 28일 11시] 11시 뉴스","contents":"<span class=\"blind\">재생시간</span>4분","link":"https://audioclip.naver.com/channels/1847/clips/26519","retrieved":1714271130110},{"title":"[04월 28일 10시] 10시 뉴스","contents":"<span class=\"blind\">재생시간</span>4분","link":"https://audioclip.naver.com/channels/1847/clips/26518","retrieved":1714269286639},{"title":"[04월 28일 09시] 9시 뉴스","contents":"<span class=\"blind\">재생시간</span>4분","link":"https://audioclip.naver.com/channels/1847/clips/26517","retrieved":1714265171130},{"title":"[04월 28일 07시] 7시 뉴스","contents":"<span class=\"blind\">재생시간</span>4분","link":"https://audioclip.naver.com/channels/1847/clips/26516","retrieved":1714259442399}]}