{"title":"오디오클립 ─ KBS 뉴스","url":"https://audioclip.naver.com/channels/1847","favicon":"https://audioclip.naver.com/channels/favicon.ico","elements":[{"title":"[05월 29일 23시] 23시 뉴스","contents":"<span class=\"blind\">재생시간</span>4분","link":"https://audioclip.naver.com/channels/1847/clips/16722","retrieved":1653837169728,"image":"https://audio-phinf.pstatic.net/20220529_75/1653833660347QA6zt_PNG/logo-icon-1024.png?type=f150_150"},{"title":"[05월 29일 22시] 22시 뉴스","contents":"<span class=\"blind\">재생시간</span>4분","link":"https://audioclip.naver.com/channels/1847/clips/16721","retrieved":1653830681124,"image":"https://audio-phinf.pstatic.net/20220529_4/16538300538694PhH2_PNG/logo-icon-1024.png?type=f150_150"},{"title":"[05월 29일 21시] KBS 뉴스 9 (1TV  수중계)","contents":"<span class=\"blind\">재생시간</span>19분","link":"https://audioclip.naver.com/channels/1847/clips/16720","retrieved":1653830681126,"image":"https://audio-phinf.pstatic.net/20220529_276/1653828278171y5vB3_PNG/logo-icon-1024.png?type=f150_150"},{"title":"[05월 29일 19시] 19시 뉴스","contents":"<span class=\"blind\">재생시간</span>4분","link":"https://audioclip.naver.com/channels/1847/clips/16719","retrieved":1653822671502,"image":"https://audio-phinf.pstatic.net/20220529_199/1653819239612LjYQA_PNG/logo-icon-1024.png?type=f150_150"},{"title":"[05월 29일 18시] 18시 뉴스","contents":"<span class=\"blind\">재생시간</span>4분","link":"https://audioclip.naver.com/channels/1847/clips/16718","retrieved":1653819200143},{"title":"[05월 29일 17시] 17시 뉴스","contents":"<span class=\"blind\">재생시간</span>4분","link":"https://audioclip.naver.com/channels/1847/clips/16717","retrieved":1653815558329},{"title":"[05월 29일 15시] 15시 뉴스","contents":"<span class=\"blind\">재생시간</span>4분","link":"https://audioclip.naver.com/channels/1847/clips/16716","retrieved":1653804942635},{"title":"[05월 29일 14시] 14시 뉴스","contents":"<span class=\"blind\">재생시간</span>4분","link":"https://audioclip.naver.com/channels/1847/clips/16715","retrieved":1653801405947},{"title":"[05월 29일 12시] 정오 종합뉴스","contents":"<span class=\"blind\">재생시간</span>9분","link":"https://audioclip.naver.com/channels/1847/clips/16714","retrieved":1653798390630},{"title":"[05월 29일 11시] 11시 뉴스","contents":"<span class=\"blind\">재생시간</span>4분","link":"https://audioclip.naver.com/channels/1847/clips/16713","retrieved":1653793507953}]}