{"title":"오디오클립 ─ KBS 뉴스","url":"https://audioclip.naver.com/channels/1847","favicon":"https://audioclip.naver.com/channels/favicon.ico","elements":[{"title":"[05월 12일 09시] 9시 뉴스","contents":"<span class=\"blind\">재생시간</span>4분","link":"https://audioclip.naver.com/channels/1847/clips/26715","retrieved":1715474885010,"image":"https://audio-phinf.pstatic.net/20230628_269/1687886470882sQaHv_PNG/logo-icon-1024.png?type=f150_150"},{"title":"[05월 12일 07시] 7시 뉴스","contents":"<span class=\"blind\">재생시간</span>4분","link":"https://audioclip.naver.com/channels/1847/clips/26714","retrieved":1715469049454,"image":"https://audio-phinf.pstatic.net/20230628_269/1687886470882sQaHv_PNG/logo-icon-1024.png?type=f150_150"},{"title":"[05월 12일 06시] 6시 뉴스","contents":"<span class=\"blind\">재생시간</span>4분","link":"https://audioclip.naver.com/channels/1847/clips/26713","retrieved":1715465352488,"image":"https://audio-phinf.pstatic.net/20230628_269/1687886470882sQaHv_PNG/logo-icon-1024.png?type=f150_150"},{"title":"[05월 12일 00시] 24시 뉴스","contents":"<span class=\"blind\">재생시간</span>4분","link":"https://audioclip.naver.com/channels/1847/clips/26712","retrieved":1715443958986,"image":"https://audio-phinf.pstatic.net/20230628_269/1687886470882sQaHv_PNG/logo-icon-1024.png?type=f150_150"},{"title":"[05월 11일 23시] 23시 뉴스","contents":"<span class=\"blind\">재생시간</span>4분","link":"https://audioclip.naver.com/channels/1847/clips/26711","retrieved":1715440187891},{"title":"[05월 11일 22시] 22시 뉴스","contents":"<span class=\"blind\">재생시간</span>4분","link":"https://audioclip.naver.com/channels/1847/clips/26710","retrieved":1715436547538},{"title":"[05월 11일 21시] KBS 뉴스 9 (1TV  수중계)","contents":"<span class=\"blind\">재생시간</span>19분","link":"https://audioclip.naver.com/channels/1847/clips/26709","retrieved":1715432991500},{"title":"[05월 11일 19시] 19시 뉴스","contents":"<span class=\"blind\">재생시간</span>4분","link":"https://audioclip.naver.com/channels/1847/clips/26708","retrieved":1715425710036},{"title":"[05월 11일 18시] 18시 뉴스","contents":"<span class=\"blind\">재생시간</span>4분","link":"https://audioclip.naver.com/channels/1847/clips/26707","retrieved":1715422267461},{"title":"[05월 11일 17시] 17시 뉴스","contents":"<span class=\"blind\">재생시간</span>4분","link":"https://audioclip.naver.com/channels/1847/clips/26706","retrieved":1715418695024}]}