{"title":"오디오클립 ─ KBS 뉴스","url":"https://audioclip.naver.com/channels/1847","favicon":"https://audioclip.naver.com/channels/favicon.ico","elements":[{"title":"[05월 29일 15시] 15시 뉴스","contents":"<span class=\"blind\">재생시간</span>4분","link":"https://audioclip.naver.com/channels/1847/clips/16716","retrieved":1653804942635,"image":"https://audio-phinf.pstatic.net/20220529_299/1653804832023G99Is_PNG/logo-icon-1024.png?type=f150_150"},{"title":"[05월 29일 14시] 14시 뉴스","contents":"<span class=\"blind\">재생시간</span>4분","link":"https://audioclip.naver.com/channels/1847/clips/16715","retrieved":1653801405947,"image":"https://audio-phinf.pstatic.net/20220529_92/1653801266963vNLJi_PNG/logo-icon-1024.png?type=f150_150"},{"title":"[05월 29일 12시] 정오 종합뉴스","contents":"<span class=\"blind\">재생시간</span>9분","link":"https://audioclip.naver.com/channels/1847/clips/16714","retrieved":1653798390630,"image":"https://audio-phinf.pstatic.net/20220529_255/1653794043674kq3gz_PNG/logo-icon-1024.png?type=f150_150"},{"title":"[05월 29일 11시] 11시 뉴스","contents":"<span class=\"blind\">재생시간</span>4분","link":"https://audioclip.naver.com/channels/1847/clips/16713","retrieved":1653793507953,"image":"https://audio-phinf.pstatic.net/20220529_68/1653790465157lgLkO_PNG/logo-icon-1024.png?type=f150_150"},{"title":"[05월 29일 10시] 10시 뉴스","contents":"<span class=\"blind\">재생시간</span>4분","link":"https://audioclip.naver.com/channels/1847/clips/16712","retrieved":1653793507955},{"title":"[05월 29일 09시] 9시 뉴스","contents":"<span class=\"blind\">재생시간</span>4분","link":"https://audioclip.naver.com/channels/1847/clips/16711","retrieved":1653785785304},{"title":"[05월 29일 07시] 7시 뉴스","contents":"<span class=\"blind\">재생시간</span>4분","link":"https://audioclip.naver.com/channels/1847/clips/16710","retrieved":1653779573647},{"title":"[05월 29일 06시] 6시 뉴스","contents":"<span class=\"blind\">재생시간</span>4분","link":"https://audioclip.naver.com/channels/1847/clips/16709","retrieved":1653775948722},{"title":"[05월 29일 00시] 24시 뉴스","contents":"<span class=\"blind\">재생시간</span>4분","link":"https://audioclip.naver.com/channels/1847/clips/16708","retrieved":1653754627040},{"title":"[05월 28일 23시] 23시 뉴스","contents":"<span class=\"blind\">재생시간</span>4분","link":"https://audioclip.naver.com/channels/1847/clips/16707","retrieved":1653750766277}]}