{"title":"오디오클립 ─ KBS 뉴스","url":"https://audioclip.naver.com/channels/1847","favicon":"https://audioclip.naver.com/channels/favicon.ico","elements":[{"title":"[12월 29일 14시] 뉴스 중계탑","contents":"<span class=\"blind\">재생시간</span>19분","link":"https://audioclip.naver.com/channels/1847/clips/19700","retrieved":1672294460997,"image":"https://audio-phinf.pstatic.net/20221229_3/1672292656030vs89V_PNG/logo-icon-1024.png?type=f150_150"},{"title":"[12월 29일 12시] 정오 종합뉴스","contents":"<span class=\"blind\">재생시간</span>19분","link":"https://audioclip.naver.com/channels/1847/clips/19699","retrieved":1672287194360,"image":"https://audio-phinf.pstatic.net/20221229_72/1672285433871WPu7v_PNG/logo-icon-1024.png?type=f150_150"},{"title":"[12월 29일 11시] 11시 뉴스","contents":"<span class=\"blind\">재생시간</span>4분","link":"https://audioclip.naver.com/channels/1847/clips/19698","retrieved":1672283521316,"image":"https://audio-phinf.pstatic.net/20221229_54/1672280031809qUuKi_PNG/logo-icon-1024.png?type=f150_150"},{"title":"[12월 29일 10시] 10시 뉴스","contents":"<span class=\"blind\">재생시간</span>4분","link":"https://audioclip.naver.com/channels/1847/clips/19697","retrieved":1672279835329,"image":"https://audio-phinf.pstatic.net/20221229_4/1672276451005uSKea_PNG/logo-icon-1024.png?type=f150_150"},{"title":"[12월 29일 09시] 9시 뉴스","contents":"<span class=\"blind\">재생시간</span>4분","link":"https://audioclip.naver.com/channels/1847/clips/19696","retrieved":1672274894798},{"title":"[12월 29일 07시] 뉴스와 화제","contents":"<span class=\"blind\">재생시간</span>19분","link":"https://audioclip.naver.com/channels/1847/clips/19695","retrieved":1672269040779},{"title":"[12월 29일 06시] KBS뉴스광장(R)","contents":"<span class=\"blind\">재생시간</span>14분","link":"https://audioclip.naver.com/channels/1847/clips/19694","retrieved":1672265405941},{"title":"[12월 29일 05시] 5시 뉴스","contents":"<span class=\"blind\">재생시간</span>4분","link":"https://audioclip.naver.com/channels/1847/clips/19693","retrieved":1672261798604},{"title":"[12월 29일 00시] 24시 뉴스","contents":"<span class=\"blind\">재생시간</span>4분","link":"https://audioclip.naver.com/channels/1847/clips/19692","retrieved":1672244028820},{"title":"[12월 28일 22시] 22시 뉴스","contents":"<span class=\"blind\">재생시간</span>4분","link":"https://audioclip.naver.com/channels/1847/clips/19691","retrieved":1672233348095}]}