{"title":"오디오클립 ─ YTN 최신 뉴스","url":"https://audioclip.naver.com/channels/197","favicon":"https://audioclip.naver.com/channels/favicon.ico","elements":[{"title":"방음 터널 최초 발화 차량, 3년 전에도 주행 중에 불","contents":"<span class=\"blind\">재생시간</span>1분","link":"https://audioclip.naver.com/channels/197/clips/60253","retrieved":1672693825629,"image":"https://audio-phinf.pstatic.net/20230103_279/1672692853367RkPec_JPEG/202301030021222201_t.jpg?type=f150_150"},{"title":"이기영, 전 애인 휴대전화로 \"바빠\"...살아있는 척 행세","contents":"<span class=\"blind\">재생시간</span>2분","link":"https://audioclip.naver.com/channels/197/clips/60252","retrieved":1672693825632,"image":"https://audio-phinf.pstatic.net/20230103_140/1672692853218SvHPP_JPEG/202301022203123578_t.jpg?type=f150_150"},{"title":"제2의 조두순 사라지나...한동훈 언급 '제시카법' 주목","contents":"<span class=\"blind\">재생시간</span>2분","link":"https://audioclip.naver.com/channels/197/clips/60251","retrieved":1672693825633,"image":"https://audio-phinf.pstatic.net/20230103_252/1672692853097dkuCb_JPEG/202301022203200394_t.jpg?type=f150_150"},{"title":"측근 '헬멧남'도 구속기소...김만배 입 열릴까","contents":"<span class=\"blind\">재생시간</span>2분","link":"https://audioclip.naver.com/channels/197/clips/60250","retrieved":1672693825635,"image":"https://audio-phinf.pstatic.net/20230103_63/1672692852983xik4y_JPEG/202301022152289600_t.jpg?type=f150_150"},{"title":"중국발 입국자 PCR 검사 의무화 첫날...\"불편하지만 감내해야죠\"","contents":"<span class=\"blind\">재생시간</span>2분","link":"https://audioclip.naver.com/channels/197/clips/60249","retrieved":1672693825637,"image":"https://audio-phinf.pstatic.net/20230103_182/1672692852852FahLo_JPEG/202301022214192898_t.jpg?type=f150_150"},{"title":"헤드라인","contents":"<span class=\"blind\">재생시간</span>1분","link":"https://audioclip.naver.com/channels/197/clips/60248","retrieved":1672693825643}]}