{"title":"오디오클립 ─ YTN 최신 뉴스","url":"https://audioclip.naver.com/channels/197","favicon":"https://audioclip.naver.com/channels/favicon.ico","elements":[{"title":"건설 노동자 또 숨져...\"소규모 사업장 관리 사각지대\"","contents":"<span class=\"blind\">재생시간</span>2분","link":"https://audioclip.naver.com/channels/197/clips/65215","retrieved":1696540226528,"image":"https://audio-phinf.pstatic.net/20231006_31/1696539195735pmSL9_JPEG/202310052307495887_t.jpg?type=f150_150"},{"title":"'문 정부 통계 조작 의혹' 강제 수사...통계청·국토부 등 전방위 압수수색","contents":"<span class=\"blind\">재생시간</span>2분","link":"https://audioclip.naver.com/channels/197/clips/65214","retrieved":1696540226529,"image":"https://audio-phinf.pstatic.net/20231006_57/1696539195604nmOjG_JPEG/202310052159334930_t.jpg?type=f150_150"},{"title":"'문 정부 통계 조작 의혹' 강제 수사...통계청·국토부 등 전방위 압수수색","contents":"<span class=\"blind\">재생시간</span>2분","link":"https://audioclip.naver.com/channels/197/clips/65213","retrieved":1696540226533,"image":"https://audio-phinf.pstatic.net/20231006_25/1696539195460tByJO_JPEG/202310052159334930_t.jpg?type=f150_150"},{"title":"오늘 대법원장 임명동의안 표결...'무기명 투표' 변수","contents":"<span class=\"blind\">재생시간</span>2분","link":"https://audioclip.naver.com/channels/197/clips/65212","retrieved":1696540226537,"image":"https://audio-phinf.pstatic.net/20231006_200/1696539195381iwy4P_JPEG/202310060101215970_t.jpg?type=f150_150"},{"title":"오늘부터 강서구청장 보궐선거 사전투표...\"총력전 돌입\"","contents":"<span class=\"blind\">재생시간</span>2분","link":"https://audioclip.naver.com/channels/197/clips/65211","retrieved":1696540226538,"image":"https://audio-phinf.pstatic.net/20231006_92/1696539195305lhw6i_JPEG/202310060008301501_t.jpg?type=f150_150"},{"title":"헤드라인","contents":"<span class=\"blind\">재생시간</span>1분","link":"https://audioclip.naver.com/channels/197/clips/65210","retrieved":1696540226545}]}