{"title":"오디오클립 ─ YTN 최신 뉴스","url":"https://audioclip.naver.com/channels/197","favicon":"https://audioclip.naver.com/channels/favicon.ico","elements":[{"title":"설 선물 대세는 '가성비'...고가 상품 세트도 증가","contents":"<span class=\"blind\">재생시간</span>3분","link":"https://audioclip.naver.com/channels/197/clips/60547","retrieved":1674098099195,"image":"https://audio-phinf.pstatic.net/20230119_247/1674096853762q7AHv_JPEG/202301190517143168_t.jpg?type=f150_150"},{"title":"내일부터 연세로에 '차 다닌다'...\"상권과 무관\" 반발","contents":"<span class=\"blind\">재생시간</span>2분","link":"https://audioclip.naver.com/channels/197/clips/60546","retrieved":1674098099196,"image":"https://audio-phinf.pstatic.net/20230119_291/16740968536115HOzH_JPEG/202301190452590890_t.jpg?type=f150_150"},{"title":"美 싱크탱크 \"한국 내 핵무기 배치 대비한 모의훈련 검토해야\"","contents":"<span class=\"blind\">재생시간</span>2분","link":"https://audioclip.naver.com/channels/197/clips/60545","retrieved":1674098099203,"image":"https://audio-phinf.pstatic.net/20230119_253/1674096853469mvdMM_JPEG/202301190818281348_t.jpg?type=f150_150"},{"title":"'김성태 영장에 與 \"李 관계 의심\"...野 \"근거 없어\"","contents":"<span class=\"blind\">재생시간</span>2분","link":"https://audioclip.naver.com/channels/197/clips/60544","retrieved":1674098099205,"image":"https://audio-phinf.pstatic.net/20230119_39/1674096853337jhe0u_JPEG/202301190952155680_t.jpg?type=f150_150"},{"title":"尹 \"대한민국 1호 영업사원\"...글로벌CEO에 '러브콜'","contents":"<span class=\"blind\">재생시간</span>2분","link":"https://audioclip.naver.com/channels/197/clips/60543","retrieved":1674098099207},{"title":"헤드라인","contents":"<span class=\"blind\">재생시간</span>1분","link":"https://audioclip.naver.com/channels/197/clips/60542","retrieved":1674098099209}]}