{"title":"오디오클립 ─ YTN 최신 뉴스","url":"https://audioclip.naver.com/channels/197","favicon":"https://audioclip.naver.com/channels/favicon.ico","elements":[{"title":"애써 평온함 유지하는 우크라이나...\"공포는 이적행위\"","contents":"<span class=\"blind\">재생시간</span>1분","link":"https://audioclip.naver.com/channels/197/clips/54451","retrieved":1644721911486,"image":"https://audio-phinf.pstatic.net/20220213_260/1644720793697399wq_JPEG/202202130422271090_t.jpg?type=f150_150"},{"title":"CJ택배 노사, 본사 점거에도 평행선...정부는 '관망'","contents":"<span class=\"blind\">재생시간</span>2분","link":"https://audioclip.naver.com/channels/197/clips/54450","retrieved":1644721911490,"image":"https://audio-phinf.pstatic.net/20220213_140/1644720793544RnmKr_JPEG/202202130526454111_t.jpg?type=f150_150"},{"title":"이번 주 김정일 생일...北 무력시위 재개할까","contents":"<span class=\"blind\">재생시간</span>1분","link":"https://audioclip.naver.com/channels/197/clips/54449","retrieved":1644721911490,"image":"https://audio-phinf.pstatic.net/20220213_28/1644720793382g8NGd_JPEG/202202130743056509_t.jpg?type=f150_150"},{"title":"대선 후보마다 '노무현 계승'...득실 예상 불가","contents":"<span class=\"blind\">재생시간</span>3분","link":"https://audioclip.naver.com/channels/197/clips/54448","retrieved":1644721911494,"image":"https://audio-phinf.pstatic.net/20220213_73/1644720793235MWyS2_JPEG/202202130521040660_t.jpg?type=f150_150"},{"title":"신규 환자 56,431명 또 역대최다...나흘 연속 5만 명대","contents":"<span class=\"blind\">재생시간</span>2분","link":"https://audioclip.naver.com/channels/197/clips/54447","retrieved":1644721911497,"image":"https://audio-phinf.pstatic.net/20220213_146/1644720793116lMSMP_JPEG/202202131008335013_t.jpg?type=f150_150"},{"title":"헤드라인","contents":"<span class=\"blind\">재생시간</span>1분","link":"https://audioclip.naver.com/channels/197/clips/54446","retrieved":1644721911504}]}