{"title":"오디오클립 ─ YTN 최신 뉴스","url":"https://audioclip.naver.com/channels/197","favicon":"https://audioclip.naver.com/channels/favicon.ico","elements":[{"title":"2500만원짜리 줄기세포 주사로 치매 완치?...환자 꼬드긴 성형외과","contents":"<span class=\"blind\">재생시간</span>3분","link":"https://audioclip.naver.com/channels/197/clips/54721","retrieved":1646017991941,"image":"https://audio-phinf.pstatic.net/20220228_1/1646016853444213UB_JPEG/202202280553479394_t.jpg?type=f150_150"},{"title":"윤석열 \"단일화 최종 결렬 통보받아\"...安 \"고려 가치 없어\"","contents":"<span class=\"blind\">재생시간</span>2분","link":"https://audioclip.naver.com/channels/197/clips/54720","retrieved":1646017991943,"image":"https://audio-phinf.pstatic.net/20220228_163/1646016853345WmLRv_JPEG/202202280006283844_t.jpg?type=f150_150"},{"title":"우크라이나 핵시설 2곳 피해...\"회담 오늘 오후 개최\"","contents":"<span class=\"blind\">재생시간</span>5분","link":"https://audioclip.naver.com/channels/197/clips/54719","retrieved":1646017991944,"image":"https://audio-phinf.pstatic.net/20220228_25/1646016853207cUUKJ_JPEG/202202280608383846_t.jpg?type=f150_150"},{"title":"우크라이나에 무기 지원 쇄도...러 항공기 하늘길 폐쇄","contents":"<span class=\"blind\">재생시간</span>2분","link":"https://audioclip.naver.com/channels/197/clips/54718","retrieved":1646017991945,"image":"https://audio-phinf.pstatic.net/20220228_51/1646016853090rimKP_JPEG/202202280633046106_t.jpg?type=f150_150"},{"title":"내일부터 식당·카페 등 방역패스 중단...신규확진 13만 9,626명","contents":"<span class=\"blind\">재생시간</span>4분","link":"https://audioclip.naver.com/channels/197/clips/54717","retrieved":1646017991946,"image":"https://audio-phinf.pstatic.net/20220228_244/1646016852988OKB6x_JPEG/202202280939487573_t.jpg?type=f150_150"},{"title":"헤드라인","contents":"<span class=\"blind\">재생시간</span>1분","link":"https://audioclip.naver.com/channels/197/clips/54716","retrieved":1646017991952}]}