{"title":"오디오클립 ─ YTN 최신 뉴스","url":"https://audioclip.naver.com/channels/197","favicon":"https://audioclip.naver.com/channels/favicon.ico","elements":[{"title":"[날씨] 29℃ 고온에 양간지풍 겹친 영동 '대형산불주의보'","contents":"<span class=\"blind\">재생시간</span>1분","link":"https://audioclip.naver.com/channels/197/clips/55429","retrieved":1649409170330,"image":"https://audio-phinf.pstatic.net/20220408_265/1649408053268lJbRw_JPEG/202204081251538273_t.jpg?type=f150_150"},{"title":"'한국인 6명' 실종 선박 이틀째 수색...외교부, '핫라인' 구축","contents":"<span class=\"blind\">재생시간</span>2분","link":"https://audioclip.naver.com/channels/197/clips/55428","retrieved":1649409170331,"image":"https://audio-phinf.pstatic.net/20220408_132/1649408053100qHyp3_JPEG/202204081645336100_t.jpg?type=f150_150"},{"title":"대검, '검수완박 반대' 공식 발표...잠시 뒤 고검장 회의 주목","contents":"<span class=\"blind\">재생시간</span>3분","link":"https://audioclip.naver.com/channels/197/clips/55427","retrieved":1649409170332,"image":"https://audio-phinf.pstatic.net/20220408_157/1649408052949OnlcL_JPEG/202204081622234742_t.jpg?type=f150_150"},{"title":"'음주측정 불응·경찰 폭행' 래퍼 장용준, 징역 1년 선고","contents":"<span class=\"blind\">재생시간</span>1분","link":"https://audioclip.naver.com/channels/197/clips/55426","retrieved":1649409170333,"image":"https://audio-phinf.pstatic.net/20220408_86/1649408052826rTD6H_JPEG/202204081627508699_t.jpg?type=f150_150"},{"title":"국민의힘, 새 원내대표에 4선 권성동 의원 선출","contents":"<span class=\"blind\">재생시간</span>4분","link":"https://audioclip.naver.com/channels/197/clips/55425","retrieved":1649409170334,"image":"https://audio-phinf.pstatic.net/20220408_84/1649408052714nhHsc_JPEG/202204081552486706_t.jpg?type=f150_150"},{"title":"헤드라인","contents":"<span class=\"blind\">재생시간</span>1분","link":"https://audioclip.naver.com/channels/197/clips/55424","retrieved":1649409170339}]}